README.md
setup.py
deepimpute/__init__.py
deepimpute/deepImpute.py
deepimpute/maskedArrays.py
deepimpute/multinet.py
deepimpute/parser.py
deepimpute/util.py
deepimpute.egg-info/PKG-INFO
deepimpute.egg-info/SOURCES.txt
deepimpute.egg-info/dependency_links.txt
deepimpute.egg-info/entry_points.txt
deepimpute.egg-info/not-zip-safe
deepimpute.egg-info/requires.txt
deepimpute.egg-info/top_level.txt