Metadata-Version: 1.0
Name: deepimpute
Version: 1.1
Summary: scRNA-seq imputation
Home-page: UNKNOWN
Author: Cedric Aridakessian
Author-email: carisdak@hawaii.edu
License: MIT
Keywords: Neural network,Deep Learning,scRNA-seq,single-cell,imputation
Platform: UNKNOWN
